{"fromERLpojo":{"contentFileName":"DeckerLite1_20191228153620.zip","uploadedTimeStamp":"20191228153606","reviewTimeStamp":"","artifactKeyPojo":{"rootNick":"DemoWinContentRoot","relevance":"MyOrg\\Divisions\\Sales","artifactName":"DeckerLite1","contentType":"DeckerLite"},"requestor":"DEMOUSER","hasSpecialHandler":true,"reviewFileName":"","erlStatus":"","author":"DEMOUSER"},"toERLpojo":{"contentFileName":"DeckerLite1_20191228154103.zip","uploadedTimeStamp":"20191228154048","reviewTimeStamp":"","artifactKeyPojo":{"rootNick":"DemoWinContentRoot","relevance":"MyOrg\\Divisions\\Sales","artifactName":"DeckerLite1","contentType":"DeckerLite"},"requestor":"DEMOUSER","hasSpecialHandler":true,"reviewFileName":"","erlStatus":"","author":"DEMOUSER"},"responseText":"Your artifact \"DeckerLite1\" of \"MyOrg\\Divisions\\Sales\" has been processed into DeckerLite1_20191228154103.zip\" of \"MyOrg\\Divisions\\Sales\""}